
<!-- 
This is the setup for SchunkHand.xml. You shouldn't need any other collision 
setup for the hand than this. The contents have been generated by a script.
-->

<CollisionSetup>
  <Exclude>

	    <FramePair first="Base" second="f1.FBase"/>
  <FramePair first="Base" second="f1.Joint1"/>
    <FramePair first="Base" second="f1.Joint2"/>
    <FramePair first="Base" second="f1.Joint3"/>
	<FramePair first="f1.FBase" second="f1.Joint1"/>
    <FramePair first="f1.Joint1" second="f1.Joint2"/>
    <FramePair first="f1.Joint1" second="f1.Joint3"/>
    <FramePair first="f1.Joint2" second="f1.Joint3"/>

	    <FramePair first="Base" second="f2.FBase"/>
    <FramePair first="Base" second="f2.Joint1"/>
    <FramePair first="Base" second="f2.Joint2"/>
    <FramePair first="Base" second="f2.Joint3"/>
	<FramePair first="f2.FBase" second="f2.Joint1"/>
    <FramePair first="f2.Joint1" second="f2.Joint2"/>
    <FramePair first="f2.Joint1" second="f2.Joint3"/>
    <FramePair first="f2.Joint2" second="f2.Joint3"/>

	
	<FramePair first="Base" second="f3.FBase"/>
    <FramePair first="Base" second="f3.Joint1"/>
    <FramePair first="Base" second="f3.Joint2"/>
    <FramePair first="Base" second="f3.Joint3"/>
	<FramePair first="f3.FBase" second="f3.Joint1"/>
    <FramePair first="f3.Joint1" second="f3.Joint2"/>
    <FramePair first="f3.Joint1" second="f3.Joint3"/>
    <FramePair first="f3.Joint2" second="f3.Joint3"/>

	</Exclude>
</CollisionSetup>
